invg.py
invg-0.0.1.dist-info/LICENSE
invg-0.0.1.dist-info/METADATA
invg-0.0.1.dist-info/WHEEL
invg-0.0.1.dist-info/top_level.txt
invg-0.0.1.dist-info/RECORD
