Metadata-Version: 2.1
Name: invg
Version: 0.0.1
Summary: Python api wrapper for INVG busstop information
Author: Moritz Schirmer
Classifier: Programming Language :: Python :: 3
Classifier: License :: OSI Approved :: MIT License
Classifier: Operating System :: OS Independent
Requires-Python: >=3.6
License-File: LICENSE
Requires-Dist: bs4
Requires-Dist: requests
